django_nested_values/__init__.py
django_nested_values/py.typed
django_nested_values/queryset.py
django_nested_values-1.0.0.dist-info/METADATA
django_nested_values-1.0.0.dist-info/WHEEL
django_nested_values-1.0.0.dist-info/licenses/LICENSE
django_nested_values-1.0.0.dist-info/RECORD
