Metadata-Version: 2.4
Name: django-nested-values
Version: 1.0.0
Summary: Add .values_nested() to Django querysets for nested prefetch dictionaries
Project-URL: Homepage, https://github.com/oliverhaas/django-nested-values
Project-URL: Documentation, https://oliverhaas.github.io/django-nested-values/
Project-URL: Repository, https://github.com/oliverhaas/django-nested-values.git
Author-email: Oliver Haas <ohaas@e1plus.de>
License: MIT
License-File: LICENSE
Keywords: django,nested,orm,prefetch_related,queryset,values
Classifier: Development Status :: 5 - Production/Stable
Classifier: Framework :: Django
Classifier: Framework :: Django :: 5.2
Classifier: Framework :: Django :: 6.0
Classifier: Intended Audience :: Developers
Classifier: License :: OSI Approved :: MIT License
Classifier: Operating System :: OS Independent
Classifier: Programming Language :: Python :: 3
Classifier: Programming Language :: Python :: 3.13
Classifier: Programming Language :: Python :: 3.14
Classifier: Topic :: Database
Classifier: Topic :: Software Development :: Libraries :: Python Modules
Classifier: Typing :: Typed
Requires-Python: >=3.13
Requires-Dist: django>=5.2
